scorpyon/SCRAP_fetching_queries.py
scorpyon/__init__.py
scorpyon/aw_editor.py
scorpyon/bull_shit_hack_because_imports_dont_work_WTF.py
scorpyon/data_source.py
scorpyon/diagnosis.py
scorpyon/dup_diag.py
scorpyon/factories.py
scorpyon/keyword_operations_base.py
scorpyon/keyword_operations_ms.py
scorpyon/khan01_spike.py
scorpyon/manip.py
scorpyon/reporting.py
scorpyon/russian_dolls.py
scorpyon/russian_dolls_CAPS.py
scorpyon/store_accessor.py
scorpyon-0.0.3.dist-info/LICENSE
scorpyon-0.0.3.dist-info/METADATA
scorpyon-0.0.3.dist-info/WHEEL
scorpyon-0.0.3.dist-info/top_level.txt
scorpyon-0.0.3.dist-info/RECORD
