Metadata-Version: 2.1
Name: scorpyon
Version: 0.0.3
Summary: Adwords utils
Home-page: https://github.com/thorwhalen/newut/tree/master/scorpyon
Author: Thor Whalen
License: mit
Platform: any
License-File: LICENSE
